setup.cfg
setup.py
bin/plus1s
plus1s/__init__.py
plus1s/errormsg.py
plus1s/start.py
plus1s.egg-info/PKG-INFO
plus1s.egg-info/SOURCES.txt
plus1s.egg-info/dependency_links.txt
plus1s.egg-info/requires.txt
plus1s.egg-info/top_level.txt
plus1s/resources/error_msgs.txt
plus1s/resources/sentences.txt
plus1s/resources/images/1.jpg
plus1s/resources/images/2.jpg
plus1s/resources/images/3.jpg