Metadata-Version: 1.0
Name: plus1s
Version: 1.1.1
Summary: Are you a real fans?
Home-page: https://github.com/ChannelOne/plus1s
Author: DZ Chan
Author-email: cdzos97@gmail.com
License: LGPL-3.0
Platform: UNKNOWN
